android_xml_converter-0.1.0.dist-info/licenses/LICENSE
main/__init__.py
main/abx2xml.py
main/xml2abx.py
android_xml_converter-0.1.0.dist-info/METADATA
android_xml_converter-0.1.0.dist-info/WHEEL
android_xml_converter-0.1.0.dist-info/entry_points.txt
android_xml_converter-0.1.0.dist-info/top_level.txt
android_xml_converter-0.1.0.dist-info/RECORD
