Metadata-Version: 2.4
Name: android-xml-converter
Version: 0.1.0
Summary: Convert between Android Binary XML and human-readable XML
Author: rhythmcache
License: Apache-2.0
Project-URL: Homepage, https://github.com/rhythmcache/android-xml-converter
Keywords: android,xml,abx,binary,converter
Classifier: Programming Language :: Python :: 3
Classifier: License :: OSI Approved :: Apache Software License
Classifier: Operating System :: OS Independent
Requires-Python: >=3.6
License-File: LICENSE
Dynamic: license-file
